wake_tests/__init__.py
wake_tests/erc20/IERC20.py
wake_tests/erc20/__init__.py
wake_tests/erc20/differential.py
wake_tests/erc20/fuzz.py
wake_tests/erc20/mock.py
wake_tests/erc20/suite_abc.py
wake_tests/erc20/suite_abi.py
wake_tests/erc20/suite_desirable.py
wake_tests/erc20/suite_fingerprint.py
wake_tests/erc20/suite_minimal.py
wake_tests/erc20/suite_recommended.py
wake_tests/erc20/utils.py
eth_wake_tests-0.1.1.dist-info/METADATA
eth_wake_tests-0.1.1.dist-info/WHEEL
eth_wake_tests-0.1.1.dist-info/RECORD
