Metadata-Version: 2.1
Name: eth-wake-tests
Version: 0.1.1
Summary: Generic tests for common Ethereum standards utilizing Wake.
Home-page: https://ackeeblockchain.com
License: ISC
Keywords: ethereum,solidity,security,testing,development,framework,audit
Author: Ackee Blockchain
Requires-Python: >=3.8,<4.0
Classifier: License :: OSI Approved
Classifier: Programming Language :: Python :: 3
Classifier: Programming Language :: Python :: 3.8
Classifier: Programming Language :: Python :: 3.9
Classifier: Programming Language :: Python :: 3.10
Classifier: Programming Language :: Python :: 3.11
Classifier: Programming Language :: Python :: 3.12
Provides-Extra: dev
Requires-Dist: eth-wake (>=4.3.2,<5.0.0)
Project-URL: Repository, https://github.com/Ackee-Blockchain/wake-tests
